codeformer/__init__.py
codeformer/codeformer.py
codeformer/codeformer_arch.py
codeformer/facelib/detection/__init__.py
codeformer/facelib/detection/align_trans.py
codeformer/facelib/detection/matlab_cp2tform.py
codeformer/facelib/detection/retinaface/retinaface.py
codeformer/facelib/detection/retinaface/retinaface_net.py
codeformer/facelib/detection/retinaface/retinaface_utils.py
codeformer/facelib/detection/yolov5face/__init__.py
codeformer/facelib/detection/yolov5face/face_detector.py
codeformer/facelib/detection/yolov5face/models/__init__.py
codeformer/facelib/detection/yolov5face/models/common.py
codeformer/facelib/detection/yolov5face/models/experimental.py
codeformer/facelib/detection/yolov5face/models/yolo.py
codeformer/facelib/detection/yolov5face/models/yolov5l.yaml
codeformer/facelib/detection/yolov5face/models/yolov5n.yaml
codeformer/facelib/detection/yolov5face/utils/__init__.py
codeformer/facelib/detection/yolov5face/utils/autoanchor.py
codeformer/facelib/detection/yolov5face/utils/datasets.py
codeformer/facelib/detection/yolov5face/utils/general.py
codeformer/facelib/detection/yolov5face/utils/torch_utils.py
codeformer/facelib/parsing/__init__.py
codeformer/facelib/parsing/bisenet.py
codeformer/facelib/parsing/parsenet.py
codeformer/facelib/parsing/resnet.py
codeformer/facelib/utils/__init__.py
codeformer/facelib/utils/face_restoration_helper.py
codeformer/facelib/utils/face_utils.py
codeformer/facelib/utils/misc.py
codeformer/realesrgan.py
codeformer/vqgan_arch.py
codeformer_perceptor-0.1.2.dist-info/LICENSE
codeformer_perceptor-0.1.2.dist-info/WHEEL
codeformer_perceptor-0.1.2.dist-info/METADATA
codeformer_perceptor-0.1.2.dist-info/RECORD
