Metadata-Version: 2.1
Name: codeformer-perceptor
Version: 0.1.2
Summary: Towards Robust Blind Face Restoration with Codebook Lookup Transformer (NeurIPS 2022)
License: S-Lab License 1.0
Author: Shangchen Zhou, Kelvin C.K. Chan, Chongyi Li, Chen Change Loy
Requires-Python: >=3.8,<4.0
Classifier: License :: Other/Proprietary License
Classifier: Programming Language :: Python :: 3
Classifier: Programming Language :: Python :: 3.8
Classifier: Programming Language :: Python :: 3.9
Classifier: Programming Language :: Python :: 3.10
Requires-Dist: Pillow (>=9.2.0,<10.0.0)
Requires-Dist: PyYAML (>=6.0,<7.0)
Requires-Dist: addict (>=2.4.0,<3.0.0)
Requires-Dist: basicsr (>=1.4.2,<2.0.0)
Requires-Dist: future (>=0.18.2,<0.19.0)
Requires-Dist: gdown (>=4.5.1,<5.0.0)
Requires-Dist: lmdb (>=1.3.0,<2.0.0)
Requires-Dist: lpips (>=0.1.4,<0.2.0)
Requires-Dist: numpy (>=1.21.5,<2.0.0)
Requires-Dist: opencv-python (>=4.6.0.66,<5.0.0.0)
Requires-Dist: requests (>=2.28.1,<3.0.0)
Requires-Dist: scikit-image (>=0.19.3,<0.20.0)
Requires-Dist: scipy (>=1.9.2,<2.0.0)
Requires-Dist: tb-nightly (>=2.11.0a20221016,<3.0.0)
Requires-Dist: torch (>=1.11.0,<2.0.0)
Requires-Dist: torchvision (<1.0.0)
Requires-Dist: tqdm (>=4.64.1,<5.0.0)
Requires-Dist: wget (>=3.2,<4.0)
Requires-Dist: yapf (>=0.32.0,<0.33.0)
